kagi/__init__.py
kagi/admin.py
kagi/apps.py
kagi/constants.py
kagi/forms.py
kagi/management/__init__.py
kagi/management/commands/__init__.py
kagi/management/commands/addbackupcode.py
kagi/migrations/0001_initial.py
kagi/migrations/__init__.py
kagi/models.py
kagi/oath.py
kagi/settings.py
kagi/static/kagi/base64js.min.js
kagi/static/kagi/webauthn.js
kagi/templates/kagi/add_key.html
kagi/templates/kagi/backup_codes.html
kagi/templates/kagi/base.html
kagi/templates/kagi/key_list.html
kagi/templates/kagi/login.html
kagi/templates/kagi/totp_device.html
kagi/templates/kagi/totpdevice_list.html
kagi/templates/kagi/two_factor_settings.html
kagi/templates/kagi/verify_second_factor.html
kagi/tests/__init__.py
kagi/tests/test_admin.py
kagi/tests/test_backups_code.py
kagi/tests/test_totp.py
kagi/tests/test_two_factor_settings.py
kagi/tests/test_util.py
kagi/tests/test_webauthn_keys.py
kagi/urls.py
kagi/util.py
kagi/views/__init__.py
kagi/views/api.py
kagi/views/backup_codes.py
kagi/views/login.py
kagi/views/mixin.py
kagi/views/totp_devices.py
kagi/views/webauthn_keys.py
kagi-0.4.0.dist-info/LICENSE
kagi-0.4.0.dist-info/METADATA
kagi-0.4.0.dist-info/WHEEL
kagi-0.4.0.dist-info/RECORD
