Metadata-Version: 2.1
Name: kagi
Version: 0.4.0
Summary: Django app for WebAuthn and TOTP-based multi-factor authentication
Home-page: https://github.com/justinmayer/kagi
License: BSD-2-Clause
Keywords: Django,WebAuthn,authentication,MFA,2FA
Author: Justin Mayer
Author-email: entroP@gmail.com
Requires-Python: >=3.7,<4.0
Classifier: Development Status :: 4 - Beta
Classifier: Environment :: Web Environment
Classifier: Framework :: Django
Classifier: Framework :: Django :: 3.2
Classifier: Framework :: Django :: 4.1
Classifier: Framework :: Django :: 4.2
Classifier: Intended Audience :: Developers
Classifier: License :: OSI Approved :: BSD License
Classifier: Operating System :: OS Independent
Classifier: Programming Language :: Python :: 3
Classifier: Programming Language :: Python :: 3.7
Classifier: Programming Language :: Python :: 3.8
Classifier: Programming Language :: Python :: 3.9
Classifier: Programming Language :: Python :: 3.10
Classifier: Programming Language :: Python :: 3.11
Classifier: Topic :: Security
Classifier: Topic :: Security :: Cryptography
Classifier: Topic :: Software Development :: Libraries :: Python Modules
Requires-Dist: Django (>=2.2)
Requires-Dist: qrcode (>=6.1,<8.0)
Requires-Dist: webauthn (>=0.4,<0.5)
Project-URL: Documentation, https://kagi.readthedocs.io
Project-URL: Issue Tracker, https://github.com/justinmayer/kagi/issues
Project-URL: Repository, https://github.com/justinmayer/kagi
